{
  "title": "02542",
  "content": "content: \"**説明:** 「シュレディンガーのねこです」と書かれた箱。中は空であるにもかかわらず、視認したものはこの箱の中に猫が存在すると確信する。\\n**回収日:** 20██/██/██\\n**回収場所:** 東京都██市の██大学\\n**現状:** サイト-81██の低危険度物品保管ロッカーに保管。\\n**追記:** この箱の制作者はシュレディンガーの猫について何か勘違いしているのではないでしょうか。 -██研究員\\nもう今更じゃないかなぁ。 -██博士\"\ntf2: '0'\nauthor: ''\nredirect-b: '[[module Redirect destination=\"http://ja.scp-wiki.net/log-of-anomalous-items-jp'\nredirect-e: '\"]]'",
  "tags": [
    "jp",
    "剪定対象-子"
  ],
  "author": "Cinderella_amber",
  "created_at": "2021-02-09T00:45:11+00:00",
  "updated_at": "2021-05-24T13:19:03+00:00",
  "rating": 6,
  "_site": "scp-jp",
  "_fullname": "anomalous-jp:02542"
}