{
  "title": "並木道のその先から",
  "content": "[[include credit:start]]\n**タイトル:** 並木道のその先から\n**著者:** ©[[*user FeS_ryuukatetu]]\n**作成年:** 2018\n----\n[[[author:fes-ryuukatetu|この著者の他の作品]]]\n[[include credit:end]]\n\n> @@@@\n> //お元気ですか？遅くなってすみませんでした。私は元気です。//\n> @@@@\n> //私を失くした人が亡くなってしまったら、私はあの場所と一緒に消えるものだと思っていました。でも実際にはその時が来ても私は消えませんでした。ただ、もう｢かくれんぼ｣はできないんだなって、漠然とした喪失感だけが残ってました。//\n> @@@@\n> //何もすることがなかったのでしばらく並木道を歩いていたら、街を見つけたんです。今までいくら歩いても並木道が続いていたのに不思議だなって。//\n> @@@@\n> //街の中も不思議な雰囲気でした。夜と、お酒と、冬の気配に満ちていました。そこで会った人たちが言うことには、ここは「忘れられてしまった者がやってくる街」なんですって。//\n> @@@@\n> //どうやらあの並木道は到着点じゃなくて通過点だったみたいです。よく考えれば確かにそうですよね。\"道\"なんですから。あの場所から消えてしまった皆にも会うことができました。//\n> @@@@\n> @@@@\n> @@@@\n> @@@@\n> //私も、忘れられちゃったんですかね。//\n> @@@@\n> @@@@\n> //忘れられたから、ここに来たんでしょうか。//\n> @@@@\n> @@@@\n> @@@@\n> @@@@\n> //いえ、違いますよね。私には分かります。あの人だけは、博士だけは私のことを覚えてくれている。//\n> @@@@\n> //でも、私のことはもう心配いりません。この街の人たちは優しいですし、皆もいます。だから、寂しくはありません。お酒はまだ飲めないけど、この街にもだんだんと馴染めてきました。//\n> @@@@\n> @@@@\n> @@@@\n> //なので、博士。//\n> @@@@\n> //もし私を気にかけてお仕事に支障が出ているようでしたら、私の事はどうぞ忘れてください。//\n> @@@@\n> //[[[SCP-461-JP|あの並木道]]]で、私とお話しをしてくれたこと。それだけで私は嬉しかったんです。心残りはありません。本当に、ありがとうございました。//\n> @@@@\n> @@@@\n> @@@@\n> //この街では手紙を送ることが慣習らしいので、それに則ってみました。少し長くなってしまったけれど、手紙の書き方もちゃんと教わって書きました。//\n> @@@@\n> //どうか、博士がこれからも幸せでありますように。//\n> @@@@\n> @@@@\n> //さようなら。//\n> @@@@\n> [[>]]\n> //[[[groups-of-interest-jp#drunkness_street|酩酊街]]]より　愛を込めて//[[/>]]\n> @@@@\n> @@@@\n> @@@@\n> @@@@\n> @@@@\n> @@@@\n> @@@@\n> @@@@\n> @@@@\n> @@@@\n> @@@@\n> @@@@\n> @@@@\n> @@@@\n> //追伸//\n> @@@@\n> @@@@\n> //ごめんなさい//\n> @@@@\n> @@@@\n> //やっぱり、一つだけ。一つだけわがままを言ってもいいですか？//\n> @@@@\n> //この手紙だけは、どうか手元に置いておいてもらえませんか。//\n> @@@@\n> //どうしても、完全に忘れられてしまうのは寂しいんです。悲しいんです。//\n> //ひょっとしたら、今でも心のどこかで博士に見つけてもらうのを待ってるのかもしれません。//\n> @@@@\n> //私、この街に来るべきじゃなかったってことなんでしょうか。//\n> @@@@\n> //手紙を書き終えてそんな事を考えていたら、街の人が言ってくれました。私は私であって、決してこの街の一部ではないと。自分の気持ちには素直になってもいいと。//\n> @@@@\n> //なので、この追伸を書きました。これが私の素直な気持ちです。//\n> @@@@\n> @@@@\n> @@@@\n> //かなり長くなってしまいましたね。//\n> @@@@\n> //それじゃあ、今度こそ。//\n> @@@@\n> @@@@\n> //さようなら、またいつか。//\n> @@@@\n> @@@@",
  "tags": [
    "jp",
    "tale",
    "酩酊街"
  ],
  "author": "FeS_ryuukatetu",
  "created_at": "2018-10-09T06:54:52+00:00",
  "updated_at": "2021-05-17T06:53:06+00:00",
  "rating": 92,
  "_site": "scp-jp",
  "_fullname": "namikimiti-no-saki"
}