{
  "title": "SCP-CN-1624",
  "content": "[[>]]\n[[module Rate]]\n[[/>]]\n\n**项目编号：**SCP-CN-1624\n\n**项目等级：**Safe\n\n**特殊收容措施：**任何与SCP-CN-1624相关的资料将被归档，基金会应当注意疑似与SCP-CN-1624相关的体操和舞蹈，若发现任何一例与SCP-CN-1624同源或SCP-CN-1624的变种时，应立即前往对涉事人员执行记忆删除，并将动作符信息提交予动作符学部进行研究。\n\n**描述：**SCP-CN-1624是一系列动作符，当对象以特定顺序完整执行后，其身体形态将会在24小时内发生变化。每一个单独步骤的SCP-CN-1624并不会展现出异常效应，系列动作符仅在以特定顺序连贯执行时才表现出异常；从中间开始或从后往前开始执行不会触发异常效应。\n\n在受影响期间，对象必须准确无误地重复完成SCP-CN-1624，异常效应才不会显现；若在此期间对象以错误的顺序执行SCP-CN-1624或停止执行SCP-CN-1624，与原本动作符不相符的肢体将会脱离对象的身体，创口被迅速增生融化的软组织与额外的皮肤覆盖，且不会造成大出血或骨骼错位。虽然这种变化在对象而言是负面的影响，但整个过程不会使对象遭受痛苦，或对象对此影响不在意。\n\nSCP-CN-1624本身施展极其困难，而且部分必须的步骤明显不符合常规/健全人类的形态，但截肢或先天残疾的对象相比常规对象更容易施展SCP-CN-1624。当前未有一例配置了假肢的对象无法执行SCP-CN-1624。\n\n若使用假体替代对象因SCP-CN-1624影响而失去的身体部分，对象报告称该部位表现出无法忍受的残肢痛。\n[[include :scp-sandbox-3:image-zoom name=http://scp-wiki-cn.wdfiles.com/local--files/SCP-CN-1624/For%20dancing.jpg|caption=Joyce Pitman博士和Lionel Pitman博士在动作符学部内研究PMK-16。|width=300px|align=right]]\n**附录：**事件报告\n\n于1858/6/17，基金会动作符学部Joyce Pitman博士和Lionel Pitman博士根据对SCP-CN-1624逆向研究，发现了若干可以反转SCP-CN-1624异常效应的动作符（编号为PMK-16），其在理论上可以使进行过截肢的对象振奋并缓解残肢痛，PMK-16常被描绘为“充满节律感”和“有生机的”。\n\n在研究期间中，Joyce Pitman博士向坐在轮椅上的Lionel Pitman博士发出完成舞蹈的邀请。虽然Lionel Pitman博士左手和右脚在此前进行过截肢手术，但在进行PMK-16过程中异常顺利且流畅完成了每一个动作，并且表现出积极心理状态；即便动作执行得不标准和准确，但并不影响其作用。\n\n事后，Joyce Pitman博士提交了关于PMK-16的研究报告，虽然后续对其可重复性研究中确实得到了相似结果，但均不足以达到理论上使对象完全忽视因配置截肢而导致幻肢痛的程度。尚不清楚在Joyce Pitman博士和Lionel Pitman博士的案例中导致PMK-16影响程度远高于其它案例的因素为何。\n\n[[footnoteblock]]\n@@@@\n[[div class=\"footer-wikiwalk-nav\"]]\n[[=]]\n<< [[[SCP-CN-1623]]] | SCP-CN-1624 | [[[SCP-CN-1625]]] >>\n[[/=]]\n[[/div]]",
  "tags": [
    "safe",
    "scp",
    "原创",
    "变形",
    "表演"
  ],
  "author": null,
  "created_at": "2020-06-20T04:41:08+00:00",
  "updated_at": "2020-07-14T01:46:32+00:00",
  "rating": 21,
  "_site": "scp-wiki-cn",
  "_fullname": "scp-cn-1624"
}