{
  "title": "日付：200█/██/██",
  "content": "[[>]]\n[[module Rate]]\n[[/>]]\n私は目を閉じながら、あの頃を思い出していた。\n世界は今より広く、でも狭く、そして色鮮やかだったころを・・・\n\n------\n\n私は当時、あまり活発な子ではなかった。\n父がいわゆる転勤族と呼ばれる部類の人間であったため、深い交友関係を築けなかったことが原因かもしれないし\nあるいはただ私が内向的であっただけかもしれない。\nあの町に住み始めたのもそんな父の転勤が理由だった。\n全く馴染めなかったわけではないが、気が付けば私は一人で町を散歩するのが夕方の日課になっていた。\n\nあの工場に出会ったのも、そんな散歩の中でだった。\n最初はただ機械が動き作業をしている男たちがなんとなく面白くて見ていた。\n無骨にして繊細な男たちの指先と機械の音が生み出す美しさが私を魅了したのだ。\n男たちと顔見知りになるのにそれほどの時間は要さず\n私が行く時間はちょうど作業が一段落することも多かった。\n今にして思えば、ちょうどいい休憩に入る口実になっていたのかもしれない。\n\nそのうち、「内緒話」をいくつかしてくれるようになった。\n「コレが今考えてる試作品の設計図だぜ坊主・・・つっても見てもわからんか！」\n豪快に笑いながら見せてくれた設計図は、男の言う通りさっぱりだった。\nおそらくはコインケースのようなもの図に様々な文字、数字、記号が描かれ、まるで美術館に飾られた絵画のよう\n唯一意味が分かった文字は「カラオケ」だけ。\nそれでも、子供に見られたくなかった私は\n「いい仕事だね」\nと、分からぬまま答える。\nその言葉に大きな笑いと、どこか誇らしげな笑顔を見せる男たちはまさに**職人**と言った風貌であったことをよく覚えている。\n\n「技術なんてもんはな、使い手次第なんだよ。ライターだってすぐに火を起こせる便利な技術の塊だが、使い方を間違えれば火事になっちまう」\n難しいか？と真剣な目をながら教えてくれたことや\n「坊主も不思議だと思ったことはどんどん調べてみな。調べたらそれを利用できないか考えてみればいい。好奇心ってのが一番大事だぜ」\nと、まるで私よりも幼い子供のような笑顔を浮かべながら話していたことを思い出す。\n\nそんな彼らと過ごす日々はあっという間に過ぎ去り、また別れの日がやってきた。\n今までは少しも悲しくなかった別れが、この時ばかりは世界の終わりに見えたものだ。\n「どうした坊主？なんか元気ねえな」\n隠そうとしても態度に出てしまう自分が悔しくて、つい口から嘘がこぼれ出した。\n「実は俺・・・今度誕生日なんだ！なんか作ってよ！！エリマキトカゲなんかに負けないようなすごいの！！！」\nその言葉は自分でも驚くほど大きく出た。まるでそれまでの態度をかき消すように。\n「お、そうだったのか。じゃあどうするかなぁ・・・」\n大声に驚いたのか、少し間が開いてから男たちが顎を掻き相談を始めようとした・・・その時だった\n\n「坊主、嘘はいかんぞ」\n私は一瞬中に浮いた。いや、浮いたと思うほど驚いた。\n私の嘘を一刀両断にして、私に話しかけてきたのは\nその工場で最も年を重ねている老人\n男たちは「工場長」と呼んでおり、私は「長老」と呼んでいた。\n「な、何のことだよ・・・」\nすでに裂かれた嘘を必死で縫い合わせるように、指を遊ばせながら私は長老と向き合う。\n「儂らはな、色んな**依頼**や**自らの好奇心**で、製品を作っておる。」\nわざわざ膝を折り、私を真正面から見据えながら長老は次の言葉を紡いだ。\n「坊主が儂らに「何か作って欲しい」と言えば、その瞬間から儂らにとっては大事な依頼主になる。だがな、儂は依頼主の嘘を一番嫌っておる」\nその眼は真剣そのもので、私はすでにその眼から逃れられなくなっていた。\n「もちろん、坊主にも事情があるのかもしれん。だが、儂は出来れば真実が知りたい」\nだめかの？と柔和な笑みと真っ直ぐとした視線に貫かれた私は\n「・・・引っ越し・・・するんだ。今週末に・・・」\n滲んだ視界の中で**真実**を口にした。\n「よく言ってくれた。最高の一品を作らせてもらうよ」\nその時の笑顔は良く覚えている。虹がかかるような最高の笑顔だった。\n\n「金曜にまた来てくれや。それまでは立ち入り禁止だ」\n企業秘密って奴だよ。と言う言葉と共に男はﾆｯと笑ってシャッターは閉じられた。\nその日から週末まで、私はその言いつけを守り工場には近づかなかった。\n\nそして、約束の日\nワクワクとした気持ちと、別れの寂しさを半分ずつ籠った足が工場に辿り着いた。\n「お、来たな。出来上がってるぜ坊主」\nいつもの男が、まるで普段と変わらない様に接してくる。\nそして工場の中には、長老が待っていた。\n「いらっしゃい。エリマキトカゲに勝てるかどうかは分からんが・・・ずっと動くものが出来とるよ」\nそう言って、長老は私に小さな金魚のおもちゃを手渡した。\n驚くほど軽く、手のひらに乗ったそれに思わず\n「なにこれ？」\nと疑問が口を突いてしまった。\n「それはな、金属を食べる金魚だよ」\n子どものような笑みを浮かべ、長老が答える。\n「食べるだけじゃねーぞ、水中を泳ぎまわるしな」\n同じ笑みを浮かべた男が、後に続いた。\n「水中に入れて、口の傍に画鋲でも置いてやればすぐに食いつく」\n長老が説明を続け、他にもいくつか注意事項を言われたはずだが\n今はもう思い出せない。\n\nだが、私が再びその軽く感じていた金魚に目を落とし\nその金魚がとても高価で貴重なものだと感じたことは\n今でも鮮明に覚えている。\n\nその後、私はその町を去った。\n「金魚」は最初こそすごいおもちゃとして私を楽しませたが\n父が転勤族から解放され、一つの街に定住するようになったころから\n私の心は金魚から少しずつ離れ始め\n段々と動かすこともなくなり\nついには押し入れの奥にしまわれることになった。\nそれでも捨てることは出来ずに\n今もこうして、持っている。\n\n------\n\n「これが、私のこの金魚との出会いですよ」\nリビングで中年の男が、思い出を語り尽くしてそういった。\n「なるほど、ご協力感謝します」\nスーツ姿の女性が頭を下げる。そのそばにはアタッシュケース、そして机の上にはレコーダーが置かれていた。\n「いえ・・・しかしこの金魚を御譲りするわけにはいきませんね」\n「どうしても・・・でしょうか？」\n「ええ、あなた方が「失われた町工場の技術を探している」と言われても、「はい、そうですか」とはなかなかね」\n頭を振りながら、男は答える。その眼に何か意志を宿して\n「なるほど。では何故今のような話を？」\n「あなた方なら、これの製作者が誰か分かるのではないか・・・という気がしましてね」\n正面から相手を見据えた男の眼には、確固たる意志が現れていた。\n「・・・それは今から調査するところです」\n「・・・なるほど、それではその調査報告を私にもお聞かせ願いたい」\n見据えた目を逸らすことなく、視線が女性を射る。\n「・・・分かりました。それでは何か分かりましたら、またご連絡を差し上げます」\n女性の方が頭を伏せ、インタビューは終わった。\n\n------\n\n男の家が視界から消えた後、女性はすぐに端末を取り出した。\n「もしもし、文月です」\n「はい、インタビューは終了しました。データは後で送ります」\n「・・・そうですね、おそらくは東弊重工についての情報は知らないと思われます」\n「はい、身辺調査は現在進行中です。3日後には結果が出ているかと」\n「オブジェクトは現在未回収ですが、調査後に回収します」\n「はい、ですので3日後に記憶処理の準備をお願いします。オブジェクトはその時に」\n失礼します。という言葉を最後にエージェントは**報告**を終えた。\n\nすっかり夕暮れとなり夜の帳が下り始めていた。\n少し肌寒い街を行きながら、先ほどの男の目を思い出しエージェント文月は呟いた。\n「貴方に強い意志がある様に、我々にも強い意志と覚悟がある。\n全てのオブジェクトを[[span class=\"ruby\"]]確保、収容、保護[[span class=\"rt\"]]Secure Contain Protect[[/span]][[/span]]せよ。という、ね。」",
  "tags": [
    "jp",
    "tale",
    "東弊重工",
    "注目記事"
  ],
  "author": "ak1-yorunaga",
  "created_at": "2014-04-22T17:09:38+00:00",
  "updated_at": "2021-01-10T15:53:04+00:00",
  "rating": 77,
  "_site": "scp-jp",
  "_fullname": "ak1-s-tales-012-jp"
}