{
  "title": "ListUsers 1",
  "content": "[[iftags +component]]\n[[div style=\"background: rgba(201,133,184,.4); box-shadow: 1px 1px 3px #999; padding: .5em;\"]]\nListUsers module for non-Wikidot users.\n\n+ How to use?\n> ##red|[[include component:listusers-1 users=\".\"]]##\n> @@##red|@@**%%name%%**@@##@@\n> ##red|[[include component:listusers-2]]##\n> @@##blue|@@**guest**@@##@@\n> ##red|[[include component:listusers-3]]##\n\n----\n* @@http://scp-wiki.wikidot.com/component:listusers-1@@\n* http://scp-wiki.wikidot.com/component:listusers-2\n* http://scp-wiki.wikidot.com/component:listusers-3\n[[/div]]\n----\n[[/iftags]]\n\n[[div class=\"textchange\"]]\n[[module ListUsers users={$users}]]\n[[div class=\"sitemember\"]]",
  "tags": [
    "component"
  ],
  "author": "7happy7",
  "created_at": "2021-02-28T13:49:47+00:00",
  "updated_at": "2021-03-07T07:20:28+00:00",
  "rating": 2,
  "_site": "scp-wiki",
  "_fullname": "component:listusers-1"
}