{
  "title": "SCP-3701-JP",
  "content": "[[include credit:start]]\n**タイトル:** SCP-3701-JP - 贖罪\n**著者:** ©[[*user Nanasi1074]]\n**作成年:** 2025\n[[include credit:end]]\n\n**アイテム番号:** SCP-3701-JP\n\n**オブジェクトクラス:** Safe\n\n**特別収容プロトコル:** SCP-3701-JPはサイト-8104の標準収容コンテナに収容されています。月に1回、サイト-8104に勤務する財団カウンセラーによって、精神面に問題がないと判断された3名の担当職員によりSCP-3701-JPの状態に変化がないか定期検査が実施されます。\n\n**説明:** SCP-3701-JPは限定的な認識災害を伴う、凡そ人間を模した高さ185cmの黒色に塗装された鉄製の像です。SCP-3701-JPは手を組んだ姿勢を取っており、目が位置すると推測される箇所には何も施された形跡がありません。SCP-3701-JPは破壊耐性を有しているため詳細な構成物は不明ですが、初期収容時に実施された重量計測の結果から内部は空洞、もしくは空洞に近いものであると推測されています。\n\nSCP-3701-JPは直接視認した人物(以下、対象と呼称)が自身が罪と認識している行為に罪悪感や後悔といったネガティブな感情を示す場合に異常性を発揮します。視認後、対象は前述した罪がSCP-3701-JPによって行われたものだと確信し、SCP-3701-JPに対して罵声を発する、叩く/蹴るといった暴行を加えます。その間、対象は女声で謝罪[[footnote]]「ごめんなさい」「私が悪かった」など。[[/footnote]]、及び感謝される旨の幻聴を知覚します。対象が満足して[[footnote]]基本的に10分から20分前後である。[[/footnote]]行為を終了した時点で、対象はSCP-3701-JPが罪を犯したという認識と保持していたネガティブな感情を喪失します。結果として殆どの場合対象の精神的健康は向上し、ストレス値の減少を示します。\n\n**__インタビュー記録: SCP-3701-JP__**\n以下はSCP-3701-JP実験後に実施されたインタビュー記録です。\n> \n> **対象:** D-4101\n> \n> **インタビュアー:** ██博士\n> \n> **付記:** D-4101は妻・子供を殺害したことによる殺人罪によりDクラス職員として雇用されています。D-4101は前述の犯行後に心的外傷後ストレス障害を発症していたこと、及び財団に対して比較的模範的な態度を取っていたため実験に選出されました。\n> \n> **<記録開始>**\n> \n> **██博士:** 早速だがD-4101、今の気分はどうかな？\n> \n> **D-4101:** 最高です。こんなに晴々とした気分でいるのは本当に久しぶりで、ずっと俺を縛ってきたものから解放されたような心地です。\n> \n> **██博士:** なるほど。今は自身が罪を犯したという自覚はあるのかい？\n> \n> //[沈黙]//\n> \n> **D-4101:** ある、と言ってもいいのでしょうか。あのときの俺はなんの根拠もなくあの像が罪を犯していて、俺は冤罪を被っていたんだと本気で信じていました。平静を失って糾弾なんかしてしまって。勿論、今はそんなことありえないと分かっています。ただ……\n> \n> **██博士:** どうした？\n> \n> **D-4101:** 俺は浮気をした妻と9歳の息子を殺しています。ですが、それは事実としてあるだけであって、新聞に書かれた事件の概要を読んでいるような感覚なんです。俺が事件に抱いていた感情は知識としてだけ残っていて、今の俺にはその実感がないんです。\n> \n> **██博士:** なるほど。君はそれを後悔しているのか？\n> \n> **D-4101:** ……わかりません。まともに考えるなら悔いるべきなんでしょうけど、どうにも感情が入らなくて。他人事のように思えてしまうんです。\n> \n> **██博士:** そうか。では君はSCP-3701-JPへの行為中に、何か声を聞かなかったか？\n> \n> **D-4101:** はい。詳しくは覚えていないですが、「ごめんなさい」だったり、「ありがとう」だったりと言われていた記憶があります。……ちょっと可笑しいですけれど。\n> \n> **██博士:** 可笑しいというのは、何か気になることが？\n> \n> **D-4101:** いや、気になるってほどでもないんですが…… 俺の罪を被って謝るのはまだ理解できるんですけど、感謝される筋合いなんてないよなと思っただけです。「ありがとう」だなんて、被虐趣味でも持っているんでしょうかね。\n> \n> [重要性の低い会話のため省略]\n> \n> **<記録終了>**\n> \n> **終了報告書:** インタビュー後の診断ではD-4101の心的外傷後ストレス障害が寛解していると示されました。\n\n**事案SCP-3701-JP(2023/11/30追記):** SCP-3701-JP実験の3日後に被験者であったD-4101がDクラス職員棟にて自殺未遂を実行したと報告されました。以下は事情聴取のために実施されたインタビュー記録です。\n\n**__インタビュー記録2: SCP-3701-JP__**\n> \n> **対象:** D-4101\n> \n> **インタビュアー:** 七篠博士\n> \n> **<記録開始>**\n> \n> **七篠博士:** ではD-4101、何故あのような行為に及んだかを教えてください。\n> \n> **D-4101:** 生きている理由を失ったからです。（間）これでは不十分ですかね。\n> \n> **七篠博士:** えぇ。失った経緯について詳しく説明してください。\n> \n> **D-4101:** 3日前の実験です。あの像に俺は理由を奪われたんです。\n> \n> **七篠博士:** SCP-3701-JPですね。しかし、貴方は当時そのようなことを報告していませんでした。何か新しく貴方の身に異常が起きたのですか？\n> \n> **D-4101:** いえ、異常は前の連絡で伝えた通りです。何も変わっていない。ただ、俺が鈍感だっただけなんです。最初は解放感で胸がいっぱいでした。ですが、翌日には違和感が、翌々日にはどうして俺が今も生きているのかが分からなくなってしまいました。\n> \n> **七篠博士:** [数秒間思案して]急な抑うつ状態に陥ったということでしょうか。それはいったい何故ですか？\n> \n> **D-4101:** 至極簡単なことで、俺には贖いが必要だったんです。許されない罪に一生を賭けて償うという思考が俺を今まで生かしてくれていたんです。\n> \n> //D-4101は俯く。//\n> \n> **D-4101:** 重苦しく感じていた、心を占有していた罪の意識の存在を俺は知っています。それが失われている今の俺は空っぽです。あの像と同じ。（間）あぁ、だから、もしかしたら。\n> \n> **七篠博士:** D-4101、どうかしましたか？\n> \n> **D-4101:** あの像は被虐趣味などではなく、ずっと許されたくないだけだったのかもしれません。それこそ、謂れのない罪であっても。\n> \n> **七篠博士:** ……どうしてそう思ったのですか？\n> \n> //[沈黙]//\n> \n> **D-4101:** 赦されてしまえば、後には何も残らないんです。……博士、俺を殺してください。妻に、息子に会いたい。\n> \n> **<記録終了>**\n> \n> **終了報告書:** D-4101は記憶処理及び擬似人格の挿入が施され、別の業務に割り振られることが決定しました。インタビュー後にSCP-3701-JPの異常性変化に関する調査が実施されましたが、収容初期時の状態と同様であったため報告書の改訂は不要と判断されました。\n\n[[footnoteblock]]",
  "tags": [],
  "author": "Nanasi1074",
  "created_at": "2025-01-25T14:41:18+00:00",
  "updated_at": "2025-01-29T14:16:54+00:00",
  "rating": -6,
  "_site": "scp-jp",
  "_fullname": "deleted:scp-3701-jp"
}