{
  "title": "SCP-2527",
  "content": "[[>]]\n[[module Rate]]\n[[/>]]\n**アイテム番号:** SCP-2527\n\n**オブジェクトクラス:** Safe\n\n**特別収容プロトコル:** 実験中以外のSCP-2527-1は、サイト-59の実験場の脇に設置されている各辺4mの立方形状をした強化鋼収容コンテナに保管します。実験はサイト管理者の指示があった場合のみ実施します。\n\nSCP-2527-2は、個別のパスワードを有する3枚のセキュリティドアの奥にある操作室で、コンピュータに挿入した状態で保管します。実験目的以外でのアクセスは固く禁じられています。SCP-2527-2を挿入したコンピュータは、実験に使用していない時はシャットダウンしてプラグを抜いてください。\n\n**説明:** SCP-2527-1は高さ2mのラマッス[[footnote]]髭を生やした人間の頭・ライオンの胴体・翼を有する[[[SCP-3740|アッシリア]]][[[SCP-2404|神話の]]][[[SCP-3615|神格]]]。[[/footnote]]の石像です。通常は不活性です。しかし、SCP-2527-2に入力されたコマンドに応じてSCP-2527-1は以下の動作が可能です。\n* 対象の前後左右に存在する3×3mの空間の中心部への瞬間的実体化による移動\n* 有機物質の焼却\n* 発生源不確定の衝撃波による壁その他の障害物の破壊\n* 3×3mの影響空間内における花その他の植生の自然発生\n* 影響空間内の機能十全な子宮内部における小型ラマッス石像の自然発生的懐胎\n\nSCP-2527-2はSCP-2527-1 の動作制御手段である、“マッシーのビッグチャンス”と題されたコモドール64テキストアドベンチャーゲームです。ゲームの箱には以下の説明書きが含まれていました ― “おぬでとう!!! 君は**マッシー、神様だ**。さぁ、全進し、支配領士を木立しよう!!!!”[[footnote]]原文: \"Congratulaton!!! You are MASSY and became a GOD. Now go fort and establis your domonion!!!!\"[[/footnote]]\n\n**SCP-2527-2ログ: 人間の被験者[[footnote]]2名のDクラス職員、D-3515およびD-5992。[[/footnote]]に対するSCP-2527-1の機能**\n\n> **マッシーノ ビッグ チャンス**\n> **VER 1.02**\n> **トトレイ ソフトウェア コーポレイション (TOTLEIGH SOFTWARE CORPORATION)**\n> \n> マッシー ハ メザメ ハコ ノ ナカ ニ イル コトニ キズイタ.\n> ハコ ノ **キタ** ニ アル **イリグチ** カラ **ヒカリ** ガ キテイル.\n> マッシー ハ **カミ** ノ ミワザ ヲ オコナウ コトヲ シンパイ シテイル.\n> ドウスル？\n> \n> > キタ ニ ムカウ\n> \n> マッシー ハ **キタ** ニ ススンダ！\n> イマ ハ ハコ ノ ソト ニ イル.\n> マッスグ **キタ** ニ 1ピキ ノ D-3515 ト D-5992 ガ ミエル.\n> シタ ニ **クサ** ガ アル.\n> \n> > キタ ニ ムカウ\n> \n> マッシー ハ **キタ** ニ ススンダ！\n> マッシー ノ オモミ ガ D-5992 ニ **オシツブシ** コウゲキ！\n> D-3515 ハ オオゴエ デ サケンデ イル.\n> D-3515 ヲ バッスル コト ガ デキルゾ.\n> \n> > d-3515 ヲ モヤス\n> \n> **ヒフ ガ モエアガル！**\n> ケタタマシイ ヒメエ ガ アガッテ イル.\n> **マッシー** ニ サカエアレ！\n> D-3515 ハ ユカノ ウエ ヲ コロガッテ イル.\n> \n> > d-3515 ヲ モヤス\n> \n> **ホノオ ガ サットウ スル！**\n> アチラ コチラ ガ モエテ イル.\n> D-3515 ハ オオイ ニ ヒメイ ヲ アゲテ イル.\n> \n> > d-3515 ニ テンバツ\n> \n> **エネルギー ノ ウェーブ！**\n> D-3515 ハ コナゴナ ニ ナッタ.\n> **マッシー** ニ サカエアレ！\n> マッシー ノ マエ ニハ トオク ニ カベ ガ ミエル.\n> **キタ**, **ヒガシ**, ソシテ **ニシ**.\n> ウシロ ニハ **ミナミ** ノ カベ, ソシテ **ハコ** ガ アル.\n> ドウスル？\n> カベ ヲ コワシテ ススモウカ？\n> \n> > ミナミ2 ニ ムカウ\n> \n> マッシー ハ **ハコ** ニ **キカン** シタ.\n> マッシー ガ **トドマル** コト ハ オススメ デキナイ.\n> カミガミ ニハ カズオオク ノ シゴト ガ マッテイル ノダ.\n> \n> > シュウリョウ\n> \n> ホント ニ イイノ？\n> \n> > y\n> \n> アリガトウ. セーブ シマシタ.",
  "tags": [
    "en",
    "safe",
    "scp",
    "ゲーム",
    "コンピュータ",
    "トトレイソフト",
    "外部エントロピー",
    "岩石",
    "彫像"
  ],
  "author": "gnmaee",
  "created_at": "2016-02-13T07:55:14+00:00",
  "updated_at": "2024-02-21T12:34:04+00:00",
  "rating": 8,
  "_site": "scp-jp",
  "_fullname": "scp-2527"
}