{
  "title": "終わりまでの回想",
  "content": "[[>]]\n[[module Rate]]\n[[/>]]\n最近よく夢を見る。\n　\nはっきりとは覚えちゃいない。でもその夢を見ると、なんとなく、難しい問題の答え合わせをした後みたいなスッキリとした気分になった。\n\n　\n俺がはっきりと覚えてる最初の記憶。\n見渡す限りの森の中。\n　\n別に気分が悪いとかそういうのはない。森は好きだ。\nでも俺は、もっと高いところにいるのが普通だと思ってた。\nずっと高い、空の上だ。\n\n他の奴らについてもそうだ。\n俺は他の奴らがいるのがわかったとき、えらく数が少ないなと感じた。そう、なぜか。\nもっと...10や20はいたような、そんな気がした。\n\n人間ってあんな見た目だったかなぁ...なんて思ったこともあったな。\n\nあとは、そうだな...なんというか...俺の頭は...もっと...。\n\n　\n　\nあぁ...いや、こういうのはあんまり考えねぇほうがいいんだろうな。\n\nただでさえどんどん頭痛が酷くなってるんだ。余計なことは考えずさっさと寝ちまおう。\n　\nまだ方法は見つかんねぇのかな。\n早くして貰いたいもんだ。そしたらこの頭痛の種も、一つ消えてくれるのによ。\n　\n　\n　\n　\n　\n　\n　\n　\n　\n　\n　\n　\n今日もまた夢を見る。\n[[span class=\"ruby\"]][[[SCP-333-JP|地球]]][[span class=\"rt\"]]あたま[[/span]][[/span]]が崩れ、生まれ変わっていく[[span class=\"ruby\"]][[[SCP-654-JP|夢]]][[span class=\"rt\"]]きおく[[/span]][[/span]] を。",
  "tags": [
    "_イベント1",
    "jp",
    "tale",
    "非公式1200字掌編企画"
  ],
  "author": "hata_suke",
  "created_at": "2016-04-18T09:38:14+00:00",
  "updated_at": "2022-07-23T16:43:29+00:00",
  "rating": 15,
  "_site": "scp-jp",
  "_fullname": "reminiscence-to-the-end"
}