{
  "title": "当游乐场的灯渐熄",
  "content": "[[>]]\n[[module rate]]\n[[/>]]\n\n[[=image ben]]\n[[=]]\n[[size 75%]]//当游乐场的灯渐熄//是The Critic-Doctor-Professor-Administrator-Reverend-Only God-Wondertainment三世死后发生的故事。\n\n游乐场的灯渐熄，而玩具与玩家们仍无限留恋。[[/size]]\n[[/=]]\n\n----\n\n[[div style=\"border:solid 1px #999999; background:#WWWWWW; padding:5px; margin-bottom: 10px;\"]]\n\n[[include component:image-block name=**image35|caption=这儿没图，没人兴奋]]\n\n**哎呦我操。**总之，你找到了一本故事集。就叫它//小小大战争2//好了，听起来还挺像个合家欢动画电影。不过这故事有前传吗？Wondertainment博士和反大麻玩家又是谁？\n\n读完它们，然后想干嘛就去干嘛。\n\n* [[[betweentheblacksheep1|幕间 其一]]]\n* 01.[[[shakepinballmachine|晃动游戏台]]]\n* 02.[[[leavingcomet|离群的彗星]]]\n* 03.[[[arcadeinvestigative|开箱检查]]]\n* 04.[[[http://scp-wiki-cn.wikidot.com/all-motley-crew|英雄集结]]] \n* 05.[[[Behind-the-scenes-interview|访谈花絮]]]\n* 06.[[[until-san-greal-are-needed-once-again|直到圣杯再现]]]\n* 07.[[[pink-eye|眼角的红色暗影]]]\n* [[[betweentheblacksheep2|幕间 其二]]]\n* 08.[[[what-happened-in-the-night|在夜晚发生什么]]]\n* 09.[[[like-i'm-talking-on-the-sunshine|在白天谈论什么]]]\n* 10.[[[imitation-redd|伪红]]]\n* 11.[[[genuine-redd|零度之炎]]]\n* 12.[[[only-thing-left-is-nightmare|迈向爱与和平的世界]]]\n//待续//\n\n[[/div]]",
  "tags": [
    "_故事中心",
    "wondertainment博士",
    "中心",
    "原创",
    "反大麻玩家",
    "小小先生"
  ],
  "author": "Chricton",
  "created_at": "2019-01-31T14:12:43+00:00",
  "updated_at": "2021-06-07T11:39:58+00:00",
  "rating": 23,
  "_site": "scp-wiki-cn",
  "_fullname": "littlegreatwargame2"
}