{
  "title": "好评",
  "content": "[[>]]\n[[module rate]]\n[[/>]]\n广袤荒漠，渺无人烟。\n\n远处的憧憧魅影还在文明的废墟中寻找牺牲品。\n\n离他们发现这里，恐怕不到10分钟了。\n\n啊，这一切究竟是从何时开始的呢？\n\n回想起来，或许从最初开始就不对劲了吧。\n----\n起先那只是一个同好者的网站。许多喜欢神秘和恐怖故事的网友聚集在一起相互交流，也有些人发表自己的创作。\n\n渐渐地，随着佳作不断涌现，我们在圈内的名气越来越大，网站用户也越来越多。\n\n自然，人越多，创作的水准也越是参差不齐。于是网站引入了评分系统。读者可以对作品进行评分，以便删除那些负分的劣作，并让高分的佳作能够获得更多的阅读量。\n\n这本来是非常合理的举措，直到……\n\n那一天，S市发生了大量伤亡的恐怖袭击案件。虽然警方很快封锁了现场，但还是有一些视频流出。\n\n视频并没有拍到犯人或者作案瞬间。不，只是世俗这样认为罢了。\n\n//但我们知道。//\n\n每一个网站的常客，都能毫不犹豫地指认出//那个雕像//，那个将出处作品推上首个达到500分地位的雕像。\n\n这也许只是巧合吧，我们这样讨论着。\n\n但很快，好奇的学生失踪在理应不存在的地下室楼梯间、整个街区的人失去了半小时记忆……500分的作品一件一件地化为现实。\n\n我们开始恐慌了。我们自己心里很清楚，500分作品列表里的故事，究竟都有些什么。\n\n网站管理员们想尽了办法。他们先是删除了评分模块，后来把精品文章都强行扣到负分，最后甚至在网站上删除了它们。\n\n没有作用。这些作品仍然存在着，存在于所有读者的记忆之中。\n\n一些人选择了自暴自弃。他们知道自己不论如何都难逃一劫，反而看得开了。他们开玩笑地将管理员们比作圣经中带来末日的天启四骑士。\n\n更多的人恐慌、疯狂、祈祷、咒骂，还有的提前自我了断。\n\n无视人们的种种意愿，精品文章中的//那些//还是一个接一个地涌现。\n\n根本不用等到最后一篇，人类文明就彻底崩溃了。余下的，就只有遍及全球的大逃杀而已。\n----\n我不知道还有多少人活着，也许几千？几万？至少我知道的人都已经死去了，要不就是比死还糟。\n\n虽然没有钟表，但我也知道，时间分分秒秒无情地流逝着。\n\n或许我还有十分钟，或许没有。\n\n但在最后的最后到来之前，我要尽力做一件事情。\n\n我不知道是否来得及完成它。如果我能早些想到就好了。\n\n作为//那个雕像//的作者，我要重写自己的作品。\n\n我要为这些神秘而恐怖的事物，添加一个守护者。\n\n这样，当它们穿越第四面墙而降临在现实世界的时候，守护者也将一并到来。人类文明仍将延续下去。\n\n我已经设计好了这个守护者的名称和标记。\n\n它的名称是——",
  "tags": [
    "2018冬季征文",
    "原创",
    "故事"
  ],
  "author": "QBLevi",
  "created_at": "2018-02-13T15:30:55+00:00",
  "updated_at": "2018-02-13T15:31:44+00:00",
  "rating": 17,
  "_site": "scp-wiki-cn",
  "_fullname": "upvoted"
}