{
  "title": "一份其貌不扬的人事档案",
  "content": "[[=]]\n[[html]]\n<iframe frameborder=\"no\" border=\"0\" marginwidth=\"0\" marginheight=\"0\" width=330 height=86 src=\"//music.163.com/outchain/player?type=2&id=1443146335&auto=0&height=66\"></iframe>\n[[/html]]\n[[/=]]\n\n[[tabview]]\n[[tab 相关记录（原创）]]\n\n**原创异常条目：**\n\n[http://scp-wiki-cn.wikidot.com/scp-cn-1356 SCP-CN-1356]\n[http://scp-wiki-cn.wikidot.com/scp-cn-1456 SCP-CN-1456]\n[http://scp-wiki-cn.wikidot.com/scp-cn-1595 SCP-CN-1595]\n[http://scp-wiki-cn.wikidot.com/scp-cn-1653 SCP-CN-1653]\n[http://scp-wiki-cn.wikidot.com/scp-cn-2309 SCP-CN-2309]\n[http://scp-wiki-cn.wikidot.com/scp-cn-2327 SCP-CN-2327]\n[http://scp-wiki-cn.wikidot.com/scp-cn-2713 SCP-CN-2713]\n[http://scp-wiki-cn.wikidot.com/scp-cn-2294 SCP-CN-2294]\n[http://scp-wiki-cn.wikidot.com/scp-cn-2395 SCP-CN-2395]\n[http://scp-wiki-cn.wikidot.com/scp-cn-2383 SCP-CN-2383]\n[http://scp-wiki-cn.wikidot.com/scp-cn-1128-ex SCP-CN-1128-EX]\n\n\n**合著异常条目：**\n\n[http://scp-wiki-cn.wikidot.com/scp-cn-2331 SCP-CN-2331]\n[http://scp-wiki-cn.wikidot.com/scp-cn-2744 SCP-CN-2744]\n\n**图书馆名单：**\n\n[http://scp-wiki-cn.wikidot.com/wanderers:far-countrys-vijndeme 远国的识府]\n[http://scp-wiki-cn.wikidot.com/wanderers:one-live-no-matter-three-stage-past 一隅人生，不期残页，三场舞台的转瞬]\n[http://scp-wiki-cn.wikidot.com/wanderers:its-our-suggest 你我之间的建议]\n[http://scp-wiki-cn.wikidot.com/wanderers:i-was-joined-a-club 我曾加入过一个社团]\n[http://scp-wiki-cn.wikidot.com/wanderers:drawing-the-period 画上句号]\n[http://scp-wiki-cn.wikidot.com/wanderers:dear-andrea 致安德烈]\n\n[[/tab]]\n[[tab 接触记录（翻译）]]\n\n**条目：**\n\n[http://scp-wiki-cn.wikidot.com/scp-5292 SCP-5292：我们如书，你们如馆，一同汇聚如今]\n[http://scp-wiki-cn.wikidot.com/scp-6120 SCP-6120：罪有其父，孽有其子]\n[http://scp-wiki-cn.wikidot.com/scp-5672 SCP-5672：避难圣所]\n[http://scp-wiki-cn.wikidot.com/scp-5421 SCP-5421：别朝上看]\n[http://scp-wiki-cn.wikidot.com/scp-5314 SCP-5314：菌之契机]\n[http://scp-wiki-cn.wikidot.com/scp-5484 SCP-5484：(地狱)电梯]\n[http://scp-wiki-cn.wikidot.com/scp-5642 SCP-5642：焦父]\n[http://scp-wiki-cn.wikidot.com/scp-5434 SCP-5434：爱神本人坠入爱河]（待重译）\n\n**外围故事：**\n\n[http://scp-wiki-cn.wikidot.com/somewhere-out-there 在某地]\n\n**GoI格式：**\n\n[http://scp-wiki-cn.wikidot.com/the-lands-nobody-returns-from 无人归来之地]\n\n**作者页：**\n\n[http://scp-wiki-cn.wikidot.com/trotskyeet-author trotskyeet的体验]\n\n**合译条目：**\n\n[http://scp-wiki-cn.wikidot.com/scp-5572 SCP-5572：我不是骨儿]\n\n\n[[/tab]]\n\n\n[[/tabview]]",
  "tags": [
    "作者"
  ],
  "author": "RalcomTheAbsurt",
  "created_at": "2022-01-12T04:05:31+00:00",
  "updated_at": "2023-12-11T14:18:12+00:00",
  "rating": 16,
  "_site": "scp-wiki-cn",
  "_fullname": "pasclomur"
}