{
  "title": "SCP-6310",
  "content": "**项目编号：**SCP-6310\n\n**项目等级：**Safe\n\n**特殊收容措施：**SCP-6310被收容在一个标准人形收容间中。直接接触SCP-6310的人员需进行有害物质处理规程的培训，并提供一次性手套、防护服和鞋套。如有必要，可为SCP-6310提供少量胶水或树脂。\n\n**描述：**SCP-6310是由聚丙烯塑料和紫色染料制成的人形机器人。虽然SCP-6310无法口头或书面交流，但它有知觉，能够与周围环境进行有限的互动。\n\nSCP-6310会持续分泌少量紫色染料（大约5mL/1天）。这种染料是非异常的，但其中含有各种高浓度的重金属（包括砷、镉、铜、铅和汞）。它不适合用作颜料。\n\nSCP-6310是脆弱的，容易损坏。这种损坏包括从小的碎片、裂缝到失去四肢。这些解体现象会使SCP-6310发生精神损伤。为了保持其正常精神状态，收容小组已被授权尽其所能修复SCP-6310。目前，已批准人员与SCP-6310进行有限制性互动。\n\n**附录：**项目被发现时，以下笔记被附于SCP-6310身上。现转载如下。相关调查还在继续。\n\n> 嘿，孩子们！你们现在是紫阁下光荣的主人啦，来自Funtastic教授的小小阁下系列！试着花时间收集所有乐趣吧！\n> @@ @@\n> 让你的阁下在这带来乐趣！找到所有阁下，超级乐趣！为你的乐趣！为你朋友的乐趣！\n> @@ @@\n> * 砰砰教授！\n> * 毛团阁下！\n> * 阁下阁下！！\n> * 小姐儿阁下！！\n> * 乐趣阁下！\n> * 洞洞阁下！\n> * 猪阁下！\n> * **紫阁下！**\n> * 美味儿阁下！\n\n[[include :scp-wiki-cn:component:license-box\n|author=Jekeled\n|translator=zhangrere128\n]]\n[!-- N/A (没有图像)  --]\n[[include :scp-wiki-cn:component:license-box-end]]",
  "tags": [
    "safe",
    "scp",
    "人形生物",
    "小小先生",
    "旧页面",
    "机器人",
    "液体",
    "金属"
  ],
  "author": "zhangrere128",
  "created_at": "2022-05-07T06:12:18+00:00",
  "updated_at": "2024-04-19T22:59:19+00:00",
  "rating": 1,
  "_site": "scp-wiki-cn",
  "_fullname": "scp-6310"
}