{
  "title": "SCP-CN-666-J",
  "content": "[[include :scp-jp:info:start]]\n翻訳責任者: [[*user fish_paste_slice]]\n翻訳年: 12 Jun 2018\t\t\n著作権者: [[*user MkoTenshi]]\t\n原題: SCP-CN-666-J - 喵喵喵\n作成年:\t23 Aug 2017\t\t\n初訳時参照リビジョン: 23 Aug 2017\t\n元記事リンク: https://scp-wiki-cn.wikidot.com/scp-cn-666-j\n[[include :scp-jp:info:end]]\n\n**アイテム番号:** SCP-CN-666-J[[footnote]] オブジェクト記事作成者のDr.Mkoは文章完成後に強制的にAクラス記憶処理を施されましたが、依然としてSCP-CN-666-Jの影響は完全には消去されていません。[[/footnote]]\n\n**オブジェクトクラス:** --もちろんSafeだ--Keter\n\n**特別収容プロトコル:** --どんな特別収容プロトコルもいらない！まったく無害！我々はこの変化を喜んで受け入れるべきだ-- SCP-CN-666-Jの数は膨大であり、人間社会にも深く浸透しているため、現在SCP-CN-666-Jを完全に収容することは不可能です。財団はSK-クラス：支配シフトシナリオへ繋がるSCP-CN-666-Jの拡散を可能な限り制限しなければなりません。\n\nSCP-CN-666-Jの異常性を発現した全てのSCP-CN-666-J-1は完全隔音の10ｍ×10ｍ×10ｍの隔音室内へ収容し--そして彼らのどんな要求も満たして--、隔音室ごとに最大で5体のSCP-CN-666-J-1を収容します。\n\nSCP-CN-666-Jの影響を受けたいかなる人間も直ちに隔離されるとともに強制的にBクラス記憶処理を施し、そして一年間継続して定期的な精神検査を受けます。二名以上のレベル4職員の許可を受けたと確認できた場合のみ、SCP-CN-666-Jへ至ったSCP-CN-666-J-1へ直接接触することが可能です。\n\n**説明:** --すばらしい--全ての猫は潜在的なSCP-CN-666-J-1であり、SCP-CN-666-JはSCP-CN-666-J-1の鳴き声、動作などが人間に対して生み出す精神影響です。SCP-CN-666-Jの影響を受けた人間（SCP-CN-666-J-2と呼称）は下記のような言動を示しますが、その言動はこれらに限定されません。：\n# 影響を与えるSCP-CN-666-J-1個体を”皇帝””猫さま”と呼称する\n# SCP-CN-666-J-1に対する関心の程度が、一般人が家猫に払うよりも著しく大きくなる\n# 性格が次第に内向的になり--我々はただの猫好きだ！--、SCP-CN-666-J-1と日常で共に過ごす時間の比率が明確に多くなる\n\nSCP-CN-666-Jの影響及びSCP-CN-666-J-1の人間社会へ溶け込んだ膨大な基数により、--猫さま--SCP-CN-666-JはSK-クラス：支配シフトシナリオ（95％以上の人類がSCP-CN-666-J-2と化し、科学技術の研究開発は人類の最低限の生存を満たす状況で”SCP-CN-666-J-1の世話をより良くする”ことに完全に傾いていると言える）を引き起こす可能性があります。--猫は世界最高の生き物-- \n[[collapsible show=\"事故記録CN-666-J-01\" hide=\"閉じる\"]]\n\n> **事故CN-666-J-01**\n> 場所: サイト-CN-21\n> 時間: 201█/██/██\n> 一匹のSCP-CN-666-J-1（以下対象と呼称）がDr.Mko（この時点で既にSCP-CN-666-Jの影響を受けている）に抱かれてサイト-CN-21へ進入し、対象が発した██という鳴き声により██名の職員の注意を引きつけ、彼らへSCP-CN-666-Jの影響を与えました。この後、オブジェクトの異常性質を認識しないまま、このサイトの██％の職員が██時間内にSCP-CN-666-Jの影響を受け、SCP-CN-666-J-2と化しました。\n> \n> **研究員R██:** あの猫はどうやってこんなに内部深くまで入ったんだ、通知無しで入るにはレベル3クリアランスが必要なんじゃないか。\n> **研究員K██:** ああ、今日はどうなっているんだ\n> **研究員R██:** ここの連中があの猫を見てた時の表情は…少しおかしかった\n> **研究員K██:** 彼らに、猫を連れて出て行くよう言わなければならないのかもしれないな…\n> 研究員K██がDr.Mkoへ、対象を連れてその場を離れるよう提案する\n> [データ削除]\n> 研究員K██は医務室へ搬送され、全てのSCP-CN-666-J-2に対してBクラス記憶処理が施された。SCP-CN-666-J-1は収容された。Dr.Mkoは隔離され一ヶ月の精神治療を施された。\n[[/collapsible]]\n[[collapsible show=\"閲覧はレベル4以上の職員にのみ限定されます。閲覧後は直ちに精神検査を行うためにサイトの医務室へ行ってください\" hide=\"閉じる\"]]\n\n\n[[=image http://scp-jp-storage.wikidot.com/local--files/file:3247157-88-z7h2/cn-666-J-re.png \twidth=\"450px\"]]\n[[/collapsible]]\n> O5-█: おい█、会議はまだ終わっていないぞ\n> O5-█: 猫に餌をやりに帰らなきゃならん\n\n[[footnoteblock]]",
  "tags": [
    "cn",
    "k-クラスシナリオ",
    "keter",
    "scp",
    "ジョーク",
    "ネコ",
    "動物",
    "画像差し止め",
    "精神影響",
    "認識災害"
  ],
  "author": "fish_paste_slice",
  "created_at": "2018-06-12T13:35:28+00:00",
  "updated_at": "2024-10-07T09:12:10+00:00",
  "rating": 38,
  "_site": "scp-jp",
  "_fullname": "scp-cn-666-j"
}