{
  "title": "한국어 기동특무부대 목록 준완본",
  "content": "**면책 조항:** 이 문서가 당신을 혼란스럽게 하고 겁먹게 만들고, 이해하기도 힘들다면, 좀 상태가 괜찮아질 때까지 [[[task-forces-ko|이쪽]]]을 읽어 보세요.\n\n이하 목록은 재단 세계관의 기동특무부대에 대한 카노니컬한 기록으로 여겨지지 //않습니다//. 이건 그저 작가들의 도구로서 의도된 것이며, 어떠한 상상의 범위에서도 '공식'으로 여겨지지 않습니다.\n\n이 목록에 없는 기동특무부대를 발견했거나, 또는 자기 SCP 항목이나 이야기에 새로운 기동특무부대를 만들었다면, 자유롭게 이 목록에 추가해도 됩니다. 이미 해당 번호를 사용하고 있는 기동특무부대가 있다면, 그 기동특무부대 아래에 새 칸을 만들어 넣으세요. 또는 반대로, 이 목록에 있는 기동특무부대가 더이상 사용되지 않거나 이름과 번호가 바뀐 것을 확인했다면, 자유롭게 수정하세요! 이건 기본적으로 공동작업 프로젝트이고, 추가적인 도움은 언제나 환영입니다. 목록에 새 항목을 더하기 위한 양식은 다음과 같습니다.\n\n[[=]]\n> @@|| 기동특무부대 번호 || 암호명 || 등장한 항목/이야기 || 간략한 설명@@[[footnote]]자기가 만든 기동특무부대라면 무엇이든 자유롭게 쓰시되, 자기가 만든 게 아니라면 되도록 포괄적 내용을 쓰세요.[[/footnote]]@@ ||@@\n[[/=]]\n\n'•' 표시가 있는 특무부대는 항목이 완전히 확인된 부대들입니다.\n\n-----\n\n++ 기동특무부대 목록\n\n||~ [[span style=\"white-space: nowrap;\"]]기동특무부대[[/span]] ||~ 암호명 ||~ 등장 문서 ||~ 작전 범위 ||\n|| ANEC-알파-1 || 밀리어먼스 || [[[SCP-979-KO]]] || SCP-979-KO 의 확산 방지 및 조작, (필요하다면) 삭제. ||\n|| • [[[task-forces-ko#alpha-17|MAF-알파-17]]] || 움츠린 날개 || [[[fmaf-hub|재단 기동항공대 허브]]] || 휘하 비행단을 통한 각종 항공 작전 수행, 그에 대한 각종 지원. ||\n|| MTF-알파-88 || 최전선 || [[[open-fire|]]] || 한반도 내 고강도 무력 개입 ||\n|| MTF-베타-9 || 위기통제반 || [[[SCP-701-KO]]], [[[SCP-717-KO]]] || 무장 인원을 통한 현장 상황 통제 등의 준전투 임무 수행. ||\n|| MTF-베타-12 || 교차로 속 신호등 ||  [[span style=\"white-space: nowrap;\"]][[[SCP-671-KO]]][[/span]] || SCP-671-KO와 혼돈의 반란 사이의 연관성 및 SCP-671-KO의 명확한 특성 파악. ||\n|| MTF-베타-2K || 빈집털이 도둑들 || [[[SCP-433-KO]]] || 격리실패, 혹은 요주의단체의 습격에 의해 무력화되었거나 그렇게 추측되는 기지에 진입하여 격리된 SCP 회수, 기밀 문서 회수 및 파쇄 등에 특화 ||\n|| MTF-감마-1 || 토끼굴 속으로 || [[[SCP-522-KO]]] || SCP-522-KO를 활용하여 요주의 단체 \"플러그소프트\"의 격리, 연구 및 교전에 특화. ||\n|| MTF-감마-64 || 디즈니 법무팀 || [[[SCP-923-KO]]] || SCP-923-KO-1의 확보와 은폐, 최종적으로는 SCP-923-KO의 완전한 격리. ||\n|| MTF-감마-100 || 스티키 핑거즈 || [[[SCP-330-KO]]] || SCP-330-KO을 확보, 처분. ||\n|| MTF-델타-1 || 형제단 || [[[SCP-984-KO]]] || SCP-984-KO에서 획득한 정보의 진위 파악 및 SCP-984-KO에 대한 역정보 전파를 위해 요주의 단체에 잠입. ||\n|| • [[[task-forces-ko#delta-17|MTF-델타-18]]] || 밈당김 || [[[SCP-515-KO]]], [[[SCP-550-KO]]], [[[SCP-627-KO]]], [/hello-your-life 당신의 삶은 안녕하십니까], [/oral-cut 구강자상], [/the-alleys-hub 골목길 허브] || 요주의 웹사이트(WoI) 감찰, 인터넷 유래 변칙 개체의 확보 및 격리. ||\n|| MTW-델타-61 || 올빼미 눈 || [[[fmaf-hub|재단 기동항공대 허브]]] || 전략/전술 항공 정찰. ||\n|| MTF-엡실론-36 || 주머니두",
  "tags": [
    "ko",
    "공동작업",
    "에세이"
  ],
  "author": "Salamander724",
  "created_at": "2017-11-08T06:47:33+00:00",
  "updated_at": "2024-12-29T16:11:28+00:00",
  "rating": 6,
  "_site": "scpko",
  "_fullname": "task-forces-complete-list-ko"
}